[
  {
    "ContainingType": "Colegio.Api.Controllers.AlumnosController",
    "Method": "GetAlumnos",
    "RelativePath": "api/Alumnos",
    "HttpMethod": "GET",
    "IsController": true,
    "Order": 0,
    "Parameters": [],
    "ReturnTypes": [
      {
        "Type": "DB.DTO.ResultDto",
        "MediaTypes": [
          "text/plain",
          "application/json",
          "text/json"
        ],
        "StatusCode": 200
      }
    ]
  },
  {
    "ContainingType": "Colegio.Api.Controllers.AlumnosController",
    "Method": "PostAlumno",
    "RelativePath": "api/Alumnos",
    "HttpMethod": "POST",
    "IsController": true,
    "Order": 0,
    "Parameters": [
      {
        "Name": "p",
        "Type": "DB.Alumnos",
        "IsRequired": true
      }
    ],
    "ReturnTypes": [
      {
        "Type": "DB.DTO.ResultDto",
        "MediaTypes": [
          "text/plain",
          "application/json",
          "text/json"
        ],
        "StatusCode": 200
      }
    ]
  },
  {
    "ContainingType": "Colegio.Api.Controllers.AlumnosController",
    "Method": "PutAlumno",
    "RelativePath": "api/Alumnos/{id}",
    "HttpMethod": "PUT",
    "IsController": true,
    "Order": 0,
    "Parameters": [
      {
        "Name": "p",
        "Type": "DB.Alumnos",
        "IsRequired": true
      },
      {
        "Name": "id",
        "Type": "System.Int32",
        "IsRequired": true
      }
    ],
    "ReturnTypes": [
      {
        "Type": "DB.DTO.ResultDto",
        "MediaTypes": [
          "text/plain",
          "application/json",
          "text/json"
        ],
        "StatusCode": 200
      }
    ]
  },
  {
    "ContainingType": "Colegio.Api.Controllers.AlumnosController",
    "Method": "DeleteAlumno",
    "RelativePath": "api/Alumnos/{id}",
    "HttpMethod": "DELETE",
    "IsController": true,
    "Order": 0,
    "Parameters": [
      {
        "Name": "id",
        "Type": "System.Int32",
        "IsRequired": true
      }
    ],
    "ReturnTypes": [
      {
        "Type": "DB.DTO.ResultDto",
        "MediaTypes": [
          "text/plain",
          "application/json",
          "text/json"
        ],
        "StatusCode": 200
      }
    ]
  },
  {
    "ContainingType": "Colegio.Api.Controllers.GruposController",
    "Method": "GetGrupos",
    "RelativePath": "api/Grupos",
    "HttpMethod": "GET",
    "IsController": true,
    "Order": 0,
    "Parameters": [],
    "ReturnTypes": [
      {
        "Type": "DB.DTO.ResultDto",
        "MediaTypes": [
          "text/plain",
          "application/json",
          "text/json"
        ],
        "StatusCode": 200
      }
    ]
  },
  {
    "ContainingType": "Colegio.Api.Controllers.GruposController",
    "Method": "PostGrupo",
    "RelativePath": "api/Grupos",
    "HttpMethod": "POST",
    "IsController": true,
    "Order": 0,
    "Parameters": [
      {
        "Name": "p",
        "Type": "DB.Grupo",
        "IsRequired": true
      }
    ],
    "ReturnTypes": [
      {
        "Type": "DB.DTO.ResultDto",
        "MediaTypes": [
          "text/plain",
          "application/json",
          "text/json"
        ],
        "StatusCode": 200
      }
    ]
  },
  {
    "ContainingType": "Colegio.Api.Controllers.GruposController",
    "Method": "PutGrupo",
    "RelativePath": "api/Grupos/{id}",
    "HttpMethod": "PUT",
    "IsController": true,
    "Order": 0,
    "Parameters": [
      {
        "Name": "id",
        "Type": "System.Int32",
        "IsRequired": true
      },
      {
        "Name": "p",
        "Type": "DB.Grupo",
        "IsRequired": true
      }
    ],
    "ReturnTypes": [
      {
        "Type": "DB.DTO.ResultDto",
        "MediaTypes": [
          "text/plain",
          "application/json",
          "text/json"
        ],
        "StatusCode": 200
      }
    ]
  },
  {
    "ContainingType": "Colegio.Api.Controllers.GruposController",
    "Method": "DeleteGrupo",
    "RelativePath": "api/Grupos/{id}",
    "HttpMethod": "DELETE",
    "IsController": true,
    "Order": 0,
    "Parameters": [
      {
        "Name": "id",
        "Type": "System.Int32",
        "IsRequired": true
      }
    ],
    "ReturnTypes": [
      {
        "Type": "DB.DTO.ResultDto",
        "MediaTypes": [
          "text/plain",
          "application/json",
          "text/json"
        ],
        "StatusCode": 200
      }
    ]
  },
  {
    "ContainingType": "Colegio.Api.Controllers.MaestroController",
    "Method": "GetMaestros",
    "RelativePath": "api/Maestro",
    "HttpMethod": "GET",
    "IsController": true,
    "Order": 0,
    "Parameters": [],
    "ReturnTypes": [
      {
        "Type": "DB.DTO.ResultDto",
        "MediaTypes": [
          "text/plain",
          "application/json",
          "text/json"
        ],
        "StatusCode": 200
      }
    ]
  },
  {
    "ContainingType": "Colegio.Api.Controllers.MaestroController",
    "Method": "PostMaestro",
    "RelativePath": "api/Maestro",
    "HttpMethod": "POST",
    "IsController": true,
    "Order": 0,
    "Parameters": [
      {
        "Name": "maestro",
        "Type": "DB.Maestro",
        "IsRequired": true
      }
    ],
    "ReturnTypes": [
      {
        "Type": "DB.DTO.ResultDto",
        "MediaTypes": [
          "text/plain",
          "application/json",
          "text/json"
        ],
        "StatusCode": 200
      }
    ]
  },
  {
    "ContainingType": "Colegio.Api.Controllers.MaestroController",
    "Method": "GetMaestro",
    "RelativePath": "api/Maestro/{id}",
    "HttpMethod": "GET",
    "IsController": true,
    "Order": 0,
    "Parameters": [
      {
        "Name": "id",
        "Type": "System.Int32",
        "IsRequired": true
      }
    ],
    "ReturnTypes": [
      {
        "Type": "DB.DTO.ResultDto",
        "MediaTypes": [
          "text/plain",
          "application/json",
          "text/json"
        ],
        "StatusCode": 200
      }
    ]
  },
  {
    "ContainingType": "Colegio.Api.Controllers.MaestroController",
    "Method": "PutMaestro",
    "RelativePath": "api/Maestro/{id}",
    "HttpMethod": "PUT",
    "IsController": true,
    "Order": 0,
    "Parameters": [
      {
        "Name": "id",
        "Type": "System.Int32",
        "IsRequired": true
      },
      {
        "Name": "maestro",
        "Type": "DB.Maestro",
        "IsRequired": true
      }
    ],
    "ReturnTypes": [
      {
        "Type": "DB.DTO.ResultDto",
        "MediaTypes": [
          "text/plain",
          "application/json",
          "text/json"
        ],
        "StatusCode": 200
      }
    ]
  },
  {
    "ContainingType": "Colegio.Api.Controllers.MaestroController",
    "Method": "DeleteMaestro",
    "RelativePath": "api/Maestro/{id}",
    "HttpMethod": "DELETE",
    "IsController": true,
    "Order": 0,
    "Parameters": [
      {
        "Name": "id",
        "Type": "System.Int32",
        "IsRequired": true
      }
    ],
    "ReturnTypes": [
      {
        "Type": "DB.DTO.ResultDto",
        "MediaTypes": [
          "text/plain",
          "application/json",
          "text/json"
        ],
        "StatusCode": 200
      }
    ]
  },
  {
    "ContainingType": "Colegio.Api.Controllers.MateriaController",
    "Method": "AddMateria",
    "RelativePath": "api/Materia",
    "HttpMethod": "POST",
    "IsController": true,
    "Order": 0,
    "Parameters": [
      {
        "Name": "materia",
        "Type": "DB.Materia",
        "IsRequired": true
      }
    ],
    "ReturnTypes": [
      {
        "Type": "DB.DTO.ResultDto",
        "MediaTypes": [
          "text/plain",
          "application/json",
          "text/json"
        ],
        "StatusCode": 200
      }
    ]
  },
  {
    "ContainingType": "Colegio.Api.Controllers.MateriaController",
    "Method": "GetMaterias",
    "RelativePath": "api/Materia",
    "HttpMethod": "GET",
    "IsController": true,
    "Order": 0,
    "Parameters": [],
    "ReturnTypes": [
      {
        "Type": "DB.DTO.ResultDto",
        "MediaTypes": [
          "text/plain",
          "application/json",
          "text/json"
        ],
        "StatusCode": 200
      }
    ]
  },
  {
    "ContainingType": "Colegio.Api.Controllers.MateriaController",
    "Method": "PutMateria",
    "RelativePath": "api/Materia/{id}",
    "HttpMethod": "PUT",
    "IsController": true,
    "Order": 0,
    "Parameters": [
      {
        "Name": "id",
        "Type": "System.Int32",
        "IsRequired": true
      },
      {
        "Name": "materia",
        "Type": "DB.Materia",
        "IsRequired": true
      }
    ],
    "ReturnTypes": [
      {
        "Type": "DB.DTO.ResultDto",
        "MediaTypes": [
          "text/plain",
          "application/json",
          "text/json"
        ],
        "StatusCode": 200
      }
    ]
  },
  {
    "ContainingType": "Colegio.Api.Controllers.MateriaController",
    "Method": "DeleteMateria",
    "RelativePath": "api/Materia/{id}",
    "HttpMethod": "DELETE",
    "IsController": true,
    "Order": 0,
    "Parameters": [
      {
        "Name": "id",
        "Type": "System.Int32",
        "IsRequired": true
      }
    ],
    "ReturnTypes": [
      {
        "Type": "DB.DTO.ResultDto",
        "MediaTypes": [
          "text/plain",
          "application/json",
          "text/json"
        ],
        "StatusCode": 200
      }
    ]
  },
  {
    "ContainingType": "Colegio.Api.Controllers.MateriasMaestroController",
    "Method": "AddMateriaMaestro",
    "RelativePath": "api/MateriasMaestro",
    "HttpMethod": "POST",
    "IsController": true,
    "Order": 0,
    "Parameters": [
      {
        "Name": "materiaMaestro",
        "Type": "DB.MateriaMaestro",
        "IsRequired": true
      }
    ],
    "ReturnTypes": [
      {
        "Type": "DB.DTO.ResultDto",
        "MediaTypes": [
          "text/plain",
          "application/json",
          "text/json"
        ],
        "StatusCode": 200
      }
    ]
  },
  {
    "ContainingType": "Colegio.Api.Controllers.MateriasMaestroController",
    "Method": "UpdateMateriaMaestro",
    "RelativePath": "api/MateriasMaestro/{id}",
    "HttpMethod": "PUT",
    "IsController": true,
    "Order": 0,
    "Parameters": [
      {
        "Name": "id",
        "Type": "System.Int32",
        "IsRequired": true
      },
      {
        "Name": "materiaMaestro",
        "Type": "DB.MateriaMaestro",
        "IsRequired": true
      }
    ],
    "ReturnTypes": [
      {
        "Type": "DB.DTO.ResultDto",
        "MediaTypes": [
          "text/plain",
          "application/json",
          "text/json"
        ],
        "StatusCode": 200
      }
    ]
  },
  {
    "ContainingType": "Colegio.Api.Controllers.MateriasMaestroController",
    "Method": "DeleteMateriaMaestro",
    "RelativePath": "api/MateriasMaestro/{idMateria}/{idMaestro}",
    "HttpMethod": "DELETE",
    "IsController": true,
    "Order": 0,
    "Parameters": [
      {
        "Name": "idMateria",
        "Type": "System.Int32",
        "IsRequired": true
      },
      {
        "Name": "idMaestro",
        "Type": "System.Int32",
        "IsRequired": true
      }
    ],
    "ReturnTypes": [
      {
        "Type": "DB.DTO.ResultDto",
        "MediaTypes": [
          "text/plain",
          "application/json",
          "text/json"
        ],
        "StatusCode": 200
      }
    ]
  },
  {
    "ContainingType": "Colegio.Api.Controllers.MateriasMaestroController",
    "Method": "GetMateriasNoAsignadasMaestro",
    "RelativePath": "api/MateriasMaestro/materias-asignadas/{idMaestro}",
    "HttpMethod": "GET",
    "IsController": true,
    "Order": 0,
    "Parameters": [
      {
        "Name": "idMaestro",
        "Type": "System.Int32",
        "IsRequired": true
      }
    ],
    "ReturnTypes": [
      {
        "Type": "DB.DTO.ResultDto",
        "MediaTypes": [
          "text/plain",
          "application/json",
          "text/json"
        ],
        "StatusCode": 200
      }
    ]
  },
  {
    "ContainingType": "Colegio.Api.Controllers.MateriasMaestroController",
    "Method": "GetMateriasMaestro",
    "RelativePath": "api/MateriasMaestro/materias-no-asignadas/{idMaestro}",
    "HttpMethod": "GET",
    "IsController": true,
    "Order": 0,
    "Parameters": [
      {
        "Name": "idMaestro",
        "Type": "System.Int32",
        "IsRequired": true
      }
    ],
    "ReturnTypes": [
      {
        "Type": "DB.DTO.ResultDto",
        "MediaTypes": [
          "text/plain",
          "application/json",
          "text/json"
        ],
        "StatusCode": 200
      }
    ]
  },
  {
    "ContainingType": "Colegio.Api.Controllers.WeatherForecastController",
    "Method": "Get",
    "RelativePath": "WeatherForecast",
    "HttpMethod": "GET",
    "IsController": true,
    "Order": 0,
    "Parameters": [],
    "ReturnTypes": [
      {
        "Type": "System.Collections.Generic.IEnumerable\u00601[[Colegio.Api.WeatherForecast, Colegio.Api, Version=1.0.0.0, Culture=neutral, PublicKeyToken=null]]",
        "MediaTypes": [
          "text/plain",
          "application/json",
          "text/json"
        ],
        "StatusCode": 200
      }
    ]
  }
]